cflaremodel/__init__.py
cflaremodel/drivers/d1_driver.py
cflaremodel/drivers/driver.py
cflaremodel/model.py
cflaremodel/query_builder.py
cflaremodel-0.1.15.dist-info/LICENSE
cflaremodel-0.1.15.dist-info/METADATA
cflaremodel-0.1.15.dist-info/WHEEL
cflaremodel-0.1.15.dist-info/RECORD
