Metadata-Version: 2.1
Name: cflaremodel
Version: 0.1.15
Summary: 
Author: Anthony Viriya
Author-email: 16130362+avltree9798@users.noreply.github.com
Requires-Python: >=3.10,<4.0
Classifier: Programming Language :: Python :: 3
Classifier: Programming Language :: Python :: 3.10
Classifier: Programming Language :: Python :: 3.11
